LICENSE.txt
MANIFEST.in
README.rst
setup.py
django_transaction_barrier/__init__.py
django_transaction_barrier/celery.py
django_transaction_barrier/models.py
django_transaction_barrier/postgresql.py
django_transaction_barrier/sqlite3.py
django_transaction_barrier.egg-info/PKG-INFO
django_transaction_barrier.egg-info/SOURCES.txt
django_transaction_barrier.egg-info/dependency_links.txt
django_transaction_barrier.egg-info/requires.txt
django_transaction_barrier.egg-info/top_level.txt
django_transaction_barrier.egg-info/zip-safe
django_transaction_barrier/migrations/0001_migration.py
django_transaction_barrier/migrations/__init__.py