Metadata-Version: 1.1
Name: django-transaction-barrier
Version: 0.3
Summary: Transaction barriers for Django and Celery.
Home-page: https://github.com/godaddy/django_transaction_barrier
Author: Silas Boyd-Wickizer
Author-email: silas@godaddy.com
License: The MIT License (MIT)
